buildout.cfg
setup.py
bootstrap/bootstrap.py
src/Interface/Attribute.py
src/Interface/Document.py
src/Interface/Exceptions.py
src/Interface/IAttribute.py
src/Interface/IElement.py
src/Interface/IInterface.py
src/Interface/IMethod.py
src/Interface/Implements.py
src/Interface/Mapping.py
src/Interface/Method.py
src/Interface/Verify.py
src/Interface/_Element.py
src/Interface/_Interface.py
src/Interface/_InterfaceClass.py
src/Interface/__init__.py
src/Interface/_object.py
src/Interface/bridge.py
src/Interface/iclass.py
src/Interface/pprint.py
src/Interface/pyskel.py
src/Interface.egg-info/PKG-INFO
src/Interface.egg-info/SOURCES.txt
src/Interface.egg-info/dependency_links.txt
src/Interface.egg-info/not-zip-safe
src/Interface.egg-info/requires.txt
src/Interface.egg-info/top_level.txt
src/Interface/Common/Mapping.py
src/Interface/Common/__init__.py
src/Interface/Common/tests/BaseTestMapping.py
src/Interface/Common/tests/__init__.py
src/Interface/tests/IFoo.py
src/Interface/tests/__init__.py
src/Interface/tests/bridge.txt
src/Interface/tests/dummy.py
src/Interface/tests/testDocument.py
src/Interface/tests/testElement.py
src/Interface/tests/testImplements.py
src/Interface/tests/testInterface.py
src/Interface/tests/testVerify.py
src/Interface/tests/testVisitImplements.py
src/Interface/tests/test_bridge.py
src/Interface/tests/unitfixtures.py
