Metadata-Version: 1.0
Name: Interface
Version: 2.11.0b1
Summary: Interface implementation
Home-page: http://cheeseshop.python.org/pypi/Interface
Author: Zope Corporation and Contributors
Author-email: zope-dev@zope.org
License: ZPL 2.1
Platform: UNKNOWN
